quazy/__init__.py
quazy/db_factory.py
quazy/db_field.py
quazy/db_protocol.py
quazy/db_query.py
quazy/db_table.py
quazy/db_types.py
quazy/exceptions.py
quazy/helpers.py
quazy/migrations.py
quazy/stub.py
quazy/translator.py
quazy/translator_psql.py
quazy/translator_sqlite.py
quazydb-1.3.6.dist-info/licenses/LICENSE
quazydb-1.3.6.dist-info/METADATA
quazydb-1.3.6.dist-info/WHEEL
quazydb-1.3.6.dist-info/top_level.txt
quazydb-1.3.6.dist-info/RECORD
