Metadata-Version: 2.4
Name: quazydb
Version: 1.3.6
Summary: Powerful yet simple Python ORM
Author-email: Andrey Aseev <andrey@aseev.biz>
Maintainer-email: Andrey Aseev <andrey@aseev.biz>
License-Expression: Apache-2.0
Project-URL: Documentation, https://quazydb.readthedocs.io/en/latest/
Project-URL: Repository, https://github.com/zergos/quazydb.git
Project-URL: Issues, https://github.com/zergos/quazydb/issues
Keywords: ORM,database,postgres,model,data
Classifier: Development Status :: 5 - Production/Stable
Classifier: Topic :: Database
Requires-Python: >=3.10
License-File: LICENSE
Requires-Dist: strenum; python_version <= "3.11"
Provides-Extra: strict
Requires-Dist: pydantic; extra == "strict"
Provides-Extra: psycopg
Requires-Dist: psycopg[binary,pool]; extra == "psycopg"
Dynamic: license-file
